{"minutes": 75, "title": "Peanut Butter Cake V", "rating": 4.02702713012695, "ingredients": ["1/2 cup all-purpose flour", "1/2 cup packed brown sugar", "1/4 cup creamy peanut butter", "3 tablespoons butter", "2 cups all-purpose flour", "1 cup packed brown sugar", "2 teaspoons baking powder", "1/2 teaspoon baking soda", "1/4 teaspoon salt", "1 cup milk", "2 eggs", "1/2 cup peanut butter", "1/4 cup butter, softened"], "instructions": "Preheat oven to 375 degrees F (190 degrees C). Grease and flour a 9x13 inch pan. Make the streusel topping: In a small bowl, combine 1/2 cup flour and 1/2 cup brown sugar. Cut in 1/4 cup peanut butter and 3 tablespoons butter until mixture resembles coarse crumbs. Set aside.\nIn a large bowl, mix together 2 cups flour, 1 cup brown sugar, baking powder, baking soda and salt. Make a well in the center and pour in the milk, eggs, 1/2 cup peanut butter and 1/4 cup butter. Mix well and pour into prepared pan. Spread evenly, then sprinkle streusel over top.\nBake in the preheated oven for 30 minutes, or until a toothpick inserted into the center of the cake comes out clean. Allow to cool.\n", "image": "https://images.media-allrecipes.com/userphotos/560x315/1014252.jpg"}