{"image": "https://images.media-allrecipes.com/userphotos/250x250/988653.jpg", "calories": "59", "rating": 4.59999990463257, "instructions": "Mix ingredients until well blended; cover.\nRefrigerate several hours to blend flavors.\nServe with red pepper strips, jicama strips, radishes, cherry tomatoes and blue corn chips.\n", "title": "All-American Summer Dip", "ingredients": ["1 (16 ounce) container BREAKSTONE'S Sour Cream", "1 envelope GOOD SEASONS Parmesan Italian or Italian Dressing Mix"], "minutes": 185}