{"ingredients": ["1 (7.75 ounce) package Betty Crocker\u00ae Suddenly Salad\u00ae classic pasta salad mix", "1 cup Roma tomatoes", "1 (2.25 ounce) can sliced ripe olives, drained", "1/2 (8 ounce) package Hormel\u00ae Pepperoni"], "title": "Peppy Pasta Salad", "instructions": "Prepare pasta salad according to package directions. Stir in pepperoni, tomatoes and olives; toss to mix well. Cover; refrigerate.\n", "rating": 3.0, "image": "https://images.media-allrecipes.com/userphotos/250x250/992056.jpg", "minutes": 30}