{"ingredients": ["1 (18 ounce) package refrigerated sugar cookie dough", "2 (8 ounce) packages cream cheese, softened", "2/3 cup packed brown sugar", "1 1/2 teaspoons vanilla extract", "1/2 cup cinnamon chips", "2 large yellow apples, peeled and thinly sliced", "1 teaspoon cinnamon sugar, or to taste", "1/8 teaspoon ground nutmeg, or to taste"], "title": "Disappearing Caramel Apple Bars", "instructions": "Preheat oven to 350 degrees F (175 degrees C).\nPress cookie dough into the bottom of a baking sheet.\nBake in the preheated oven until light-golden brown, 10 to 12 minutes. Remove from oven and cool completely.\nMix cream cheese, brown sugar, and vanilla extract together in a bowl until smooth; fold in cinnamon chips. Spread cream cheese mixture over cooled cookie and layer with apple slices. Sprinkle cinnamon sugar and nutmeg over apple slice layer. Cut into squares.\n", "rating": 5.0, "image": "https://images.media-allrecipes.com/userphotos/560x315/1594848.jpg", "minutes": 60}