{"ingredients": ["1 packet sazon seasoning, or more to taste", "1 pinch freshly cracked black pepper, or to taste", "2 pounds untrimmed skirt steak, or more to taste", "2 green bell peppers, seeded and diced", "2 red bell peppers, seeded and diced", "1 large onion, diced", "6 cloves garlic, minced"], "title": "Churrasco (Stewed Skirt Steak) with Peppers and Onions", "instructions": "Preheat oven to 325 degrees F (165 degrees C).\nSprinkle sazon seasoning and black pepper over steaks; rub in lightly with your fingers. Arrange steaks close together, but not overlapping, in a large casserole dish.\nMix green bell peppers, red bell peppers, onion, and garlic together in a large bowl. Spoon over steaks in the casserole dish. Cover with aluminum foil.\nBake in the preheated oven until peppers are soft and steaks are cooked through, 1 1/2 to 2 hours.\n", "rating": 4.0, "image": "https://images.media-allrecipes.com/userphotos/560x315/3958799.jpg", "minutes": 115}