{"image": "https://images.media-allrecipes.com/userphotos/250x250/702777.jpg", "calories": "724", "rating": 4.44978189468384, "instructions": "In a pot with enough water to cover, boil the chicken 25 minutes, or until juices run clear. Drain, cool, and shred.\nPreheat oven to 350 degrees F (175 degrees C). Lightly grease a medium baking dish.\nFill each tortilla with equal amounts of chicken and cheese, reserving 1/4 cup cheese for topping. Roll tortillas to form enchiladas. Arrange enchiladas in the prepared baking dish. Cover with the enchilada sauce.\nBake enchiladas 30 minutes in the preheated oven. Top with reserved cheese, and continue baking 5 minutes, until cheese is melted.\n", "title": "Green Chicken Enchilada", "ingredients": ["1 pound skinless, boneless chicken breast halves", "12 (10 inch) flour tortillas", "1 (8 ounce) package shredded Monterey Jack cheese", "1 (19 ounce) can green enchilada sauce"], "minutes": 75}